magellan_models/__init__.py
magellan_models/config/__init__.py
magellan_models/config/magellan_config.py
magellan_models/exceptions/__init__.py
magellan_models/exceptions/magellan_exception.py
magellan_models/exceptions/magellan_warning.py
magellan_models/initializers/__init__.py
magellan_models/initializers/initialize_with_endpoint.py
magellan_models/initializers/initialize_with_json.py
magellan_models/initializers/initialize_with_yaml.py
magellan_models/interface/__init__.py
magellan_models/interface/abstract_api_model.py
magellan_models/interface/auto_dict.py
magellan_models/interface/constant_magellan_response.py
magellan_models/interface/magellan_response.py
magellan_models/model_generator/__init__.py
magellan_models/model_generator/generate_dynamic_model.py
magellan_models/model_generator/generate_from_spec.py
magellan_models/model_generator/generate_nonrest_functions.py
magellan_models/model_generator/generic_functions_generator.py
magellan_models/model_generator/helper_funcs.py
magellan_models/model_generator/json_schema_attribute_extractor.py
magellan_models/model_generator/model_parser.py
magellan_models/model_generator/openapi_parser.py
tests/__init__.py
tests/conftest.py
tests/helper.py
tests/generator_tests/__init__.py
tests/generator_tests/test_custom_attribute_paths.py
tests/generator_tests/test_disabled_funcs.py
tests/generator_tests/test_init_with_endpoint.py
tests/generator_tests/test_json_schema_attribute_extractor.py
tests/generator_tests/test_non_rest_parsing.py
tests/generator_tests/test_regex_id_sep.py
tests/generator_tests/test_relationship_categorizing.py
tests/integration_tests/__init__.py
tests/integration_tests/test_config.py
tests/integration_tests/test_find_by_models_generated.py
tests/integration_tests/test_generated_attributes.py
tests/integration_tests/test_generic_funcs.py
tests/integration_tests/test_relationship_methods_work.py
magellan_models-1.0.0.dist-info/LICENSE
magellan_models-1.0.0.dist-info/METADATA
magellan_models-1.0.0.dist-info/WHEEL
magellan_models-1.0.0.dist-info/top_level.txt
magellan_models-1.0.0.dist-info/RECORD
