Metadata-Version: 2.1
Name: magellan-models
Version: 1.0.0
Summary: An API wrapper library that creates 'ActiveRecord' inspired models to access JSON:API compliant endpoints via OpenAPI specifications
Home-page: https://github.com/3mcloud/magellan-models
Author: Talha Ahsan
Author-email: tahsan@mmm.com
License: UNKNOWN
Platform: UNKNOWN
Classifier: Programming Language :: Python :: 3
Classifier: License :: OSI Approved :: BSD License
Classifier: Operating System :: OS Independent
Requires-Python: >=3.6
Requires-Dist: requests (>=2.24.0)
Requires-Dist: inflection (>=0.5.0)
Requires-Dist: pyyaml (>=5.4.1)
Requires-Dist: jsonschema (>=3.2.0)
Provides-Extra: dev
Requires-Dist: pytest (>=5.4.3) ; extra == 'dev'
Requires-Dist: pytest-cov (>=2.10.0) ; extra == 'dev'
Requires-Dist: requests-mock (>=1.8.0) ; extra == 'dev'
Requires-Dist: coverage (>=5.2) ; extra == 'dev'
Requires-Dist: pytest-mock (>=3.6.1) ; extra == 'dev'
Provides-Extra: docs
